helaocore/__init__.py
helaocore/error.py
helaocore/helaodict.py
helaocore/models/__init__.py
helaocore/models/action.py
helaocore/models/action_start_condition.py
helaocore/models/analysis.py
helaocore/models/credentials.py
helaocore/models/data.py
helaocore/models/electrolyte.py
helaocore/models/experiment.py
helaocore/models/file.py
helaocore/models/helaodirs.py
helaocore/models/hlostatus.py
helaocore/models/machine.py
helaocore/models/orchstatus.py
helaocore/models/process.py
helaocore/models/process_contrib.py
helaocore/models/run_use.py
helaocore/models/s3locator.py
helaocore/models/sample.py
helaocore/models/sequence.py
helaocore/models/server.py
helaocore/version.py
helaocore-2023.4.11.dist-info/LICENSE
helaocore-2023.4.11.dist-info/METADATA
helaocore-2023.4.11.dist-info/WHEEL
helaocore-2023.4.11.dist-info/RECORD
