Metadata-Version: 2.1
Name: helaocore
Version: 2023.4.11
Summary: The core codebase for the HELAO High Throughoutput Experimentation code base.
Author: Matthias Richter
Author-email: mrichter@caltech.edu
Requires-Python: >=3.8,<4.0
Classifier: Programming Language :: Python :: 3
Classifier: Programming Language :: Python :: 3.8
Classifier: Programming Language :: Python :: 3.9
Classifier: Programming Language :: Python :: 3.10
Classifier: Programming Language :: Python :: 3.11
Requires-Dist: pydantic (>=1.9.1,<2.0.0)
